mikagram_sessions/__init__.py
mikagram_sessions/alias/__init__.py
mikagram_sessions/alias/pathlike.py
mikagram_sessions/constants/__init__.py
mikagram_sessions/constants/apps.py
mikagram_sessions/constants/dcs.py
mikagram_sessions/sessions/__init__.py
mikagram_sessions/sessions/defaults.py
mikagram_sessions/sessions/json_session.py
mikagram_sessions/sessions/pyrogram.py
mikagram_sessions/sessions/session.py
mikagram_sessions/sessions/sqlite.py
mikagram_sessions/sessions/telethon_.py
mikagram_sessions/types/__init__.py
mikagram_sessions/types/other/__init__.py
mikagram_sessions/types/other/api_application.py
mikagram_sessions/types/sessions/__init__.py
mikagram_sessions/types/sessions/json_session.py
mikagram_sessions-0.1.1.dist-info/METADATA
mikagram_sessions-0.1.1.dist-info/WHEEL
mikagram_sessions-0.1.1.dist-info/top_level.txt
mikagram_sessions-0.1.1.dist-info/RECORD
