Metadata-Version: 2.4
Name: Mikagram-Sessions
Version: 0.1.1
Summary: Mikagram's sessions
Requires-Python: >=3.9
